formatslackmessage/__init__.py
formatslackmessage/formatslackoutput.py
formatSlackMessage-1.0.4.dist-info/LICENSE.md
formatSlackMessage-1.0.4.dist-info/METADATA
formatSlackMessage-1.0.4.dist-info/WHEEL
formatSlackMessage-1.0.4.dist-info/top_level.txt
formatSlackMessage-1.0.4.dist-info/RECORD
