Metadata-Version: 2.1
Name: formatSlackMessage
Version: 1.0.4
Summary: A project to format the slack messages in a structured way
Author: Bilal Peerzade
Author-email: bilalpeerzade@gmail.com
Keywords: formatmessage,slackoutput,slack,format
Classifier: Programming Language :: Python :: 2.7
Classifier: License :: OSI Approved :: MIT License
Classifier: Operating System :: Unix
Classifier: Development Status :: 5 - Production/Stable
License-File: LICENSE.md
Requires-Dist: pandas (>=1.1.5)
